thehellmaker_lib_3/__init__.py
thehellmaker_lib_3/main.py
thehellmaker_lib_3-0.1.1.dist-info/METADATA
thehellmaker_lib_3-0.1.1.dist-info/WHEEL
thehellmaker_lib_3-0.1.1.dist-info/RECORD
