Metadata-Version: 2.4
Name: thehellmaker-lib-3
Version: 0.1.1
Summary: Add your description here
Requires-Python: >=3.12.3
Requires-Dist: thehellmaker-lib-1==0.1.4
